bwinterface/__init__.py
bwinterface/bwinterface.py
bwinterface-0.2.0.dist-info/LICENSE
bwinterface-0.2.0.dist-info/METADATA
bwinterface-0.2.0.dist-info/WHEEL
bwinterface-0.2.0.dist-info/top_level.txt
bwinterface-0.2.0.dist-info/RECORD
