Metadata-Version: 2.1
Name: bwinterface
Version: 0.2.0
Summary: access the Bitwarden/Vaultwarden CLI ("bw") conveniently
Home-page: https://www.github.com/towalink/bwinterface
Author: Dirk Henrici
Author-email: towalink.bwinterface@henrici.name
Project-URL: Repository, https://www.github.com/towalink/bwinterface
Project-URL: PyPi, https://pypi.org/project/bwinterface/
Keywords: Bitwarden Vaultwarden wrapper interface
Classifier: Programming Language :: Python
Classifier: License :: OSI Approved :: MIT License
Classifier: Operating System :: POSIX :: Linux
Classifier: Development Status :: 3 - Alpha
Classifier: Intended Audience :: System Administrators
Classifier: Intended Audience :: Developers
Classifier: Intended Audience :: Information Technology
Requires-Python: >=3.7
License-File: LICENSE
